evil_winrm_py/__init__.py
evil_winrm_py/evil_winrm_py.py
evil_winrm_py/_ps/__init__.py
evil_winrm_py/_ps/fetch.ps1
evil_winrm_py/_ps/send.ps1
evil_winrm_py/pypsrp_ewp/__init__.py
evil_winrm_py/pypsrp_ewp/wsman.py
evil_winrm_py-1.5.0.dist-info/licenses/LICENSE
evil_winrm_py-1.5.0.dist-info/METADATA
evil_winrm_py-1.5.0.dist-info/WHEEL
evil_winrm_py-1.5.0.dist-info/entry_points.txt
evil_winrm_py-1.5.0.dist-info/top_level.txt
evil_winrm_py-1.5.0.dist-info/RECORD
