Metadata-Version: 2.4
Name: evil-winrm-py
Version: 1.5.0
Summary: Execute commands interactively on remote Windows machines using the WinRM protocol
Home-page: https://github.com/adityatelange/evil-winrm-py
Download-URL: https://github.com/adityatelange/evil-winrm-py/archive/v1.5.0.zip
Author: adityatelange
License: MIT
Classifier: Topic :: Security
Classifier: Operating System :: Unix
Classifier: License :: OSI Approved :: MIT License
Classifier: Programming Language :: Python :: 3
Requires-Python: >=3.9
License-File: LICENSE
Requires-Dist: pypsrp==0.8.1
Requires-Dist: prompt_toolkit==3.0.52
Requires-Dist: tqdm==4.67.1
Provides-Extra: kerberos
Requires-Dist: pypsrp[kerberos]==0.8.1; extra == "kerberos"
Dynamic: author
Dynamic: classifier
Dynamic: description
Dynamic: description-content-type
Dynamic: download-url
Dynamic: home-page
Dynamic: license
Dynamic: license-file
Dynamic: provides-extra
Dynamic: requires-dist
Dynamic: requires-python
Dynamic: summary
